csst/__init__.py
csst/common/__init__.py
csst/common/data.py
csst/common/exception.py
csst/common/processors.py
csst/msc/__init__.py
csst/msc/data.py
csst/msc/instrument.py
csst/msc/astrometry/__init__.py
csst/msc/astrometry/raw/__init__.py
csst/msc/astrometry/raw/run_astrom_csst.py
csst-0.0.4.dist-info/LICENSE
csst-0.0.4.dist-info/METADATA
csst-0.0.4.dist-info/WHEEL
csst-0.0.4.dist-info/top_level.txt
csst-0.0.4.dist-info/RECORD
